am4894bq/__init__.py
am4894bq/_nbdev.py
am4894bq/core.py
am4894bq/pd.py
am4894bq/schema.py
am4894bq/utils.py
am4894bq-0.1.34.dist-info/LICENSE
am4894bq-0.1.34.dist-info/METADATA
am4894bq-0.1.34.dist-info/WHEEL
am4894bq-0.1.34.dist-info/top_level.txt
am4894bq-0.1.34.dist-info/RECORD
