Metadata-Version: 2.1
Name: am4894bq
Version: 0.1.34
Summary: Helper library for BigQuery
Home-page: https://github.com/andrewm4894/am4894bq/tree/master/
Author: Andrew Maguire
Author-email: andrewm4894@gmail.com
License: Apache Software License 2.0
Keywords: bigquery
Platform: UNKNOWN
Classifier: Development Status :: 3 - Alpha
Classifier: Intended Audience :: Developers
Classifier: License :: OSI Approved :: Apache Software License
Classifier: Natural Language :: English
Classifier: Programming Language :: Python :: 3.6
Classifier: Programming Language :: Python :: 3.7
Classifier: Programming Language :: Python :: 3.8
Requires-Python: >=3.6
License-File: LICENSE
Requires-Dist: python-dotenv
Requires-Dist: google-cloud-bigquery[bqstorage,pandas]
Requires-Dist: pandas-gbq
